instagram_autoresponder/__init__.py
instagram_autoresponder/instagram_autoresponder.py
run.py
instagram_autoresponder-0.0.2a2.dist-info/LICENSE
instagram_autoresponder-0.0.2a2.dist-info/METADATA
instagram_autoresponder-0.0.2a2.dist-info/WHEEL
instagram_autoresponder-0.0.2a2.dist-info/entry_points.txt
instagram_autoresponder-0.0.2a2.dist-info/RECORD
