Metadata-Version: 2.1
Name: instagram-autoresponder
Version: 0.0.2a2
Summary: Automatically respond to Instagram direct messages based on predefined rules.
License: LICENSE
Author: Shubham Raj
Author-email: shubhamraj2202@gmail.com
Requires-Python: >=3.11,<4.0
Classifier: License :: Other/Proprietary License
Classifier: Programming Language :: Python :: 3
Classifier: Programming Language :: Python :: 3.11
Classifier: Programming Language :: Python :: 3.12
Requires-Dist: Pillow
Requires-Dist: instagrapi
